Workbook

Sheet 📒 Ledger
A1: MR MALLORCA GOLF — AUTÓNOMO INCOME & EXPENSE LEDGER 2026
A2: Andy Griffiths · NIE Z1985059A · CNAE 8551 · IAE 826 · Alta 26/05/2026
A4: Date | B4: Invoice # | C4: Client / Supplier | D4: Description | E4: Income (€) | F4: Expense (€) | G4: Quarter | H4: Receipt? | I4: Notes
G5: =IF(A5="","",IF(MONTH(A5)<=3,"Q1",IF(MONTH(A5)<=6,"Q2",IF(MONTH(A5)<=9,"Q3","Q4"))))
G6: =IF(A6="","",IF(MONTH(A6)<=3,"Q1",IF(MONTH(A6)<=6,"Q2",IF(MONTH(A6)<=9,"Q3","Q4"))))
G7: =IF(A7="","",IF(MONTH(A7)<=3,"Q1",IF(MONTH(A7)<=6,"Q2",IF(MONTH(A7)<=9,"Q3","Q4"))))
G8: =IF(A8="","",IF(MONTH(A8)<=3,"Q1",IF(MONTH(A8)<=6,"Q2",IF(MONTH(A8)<=9,"Q3","Q4"))))
G9: =IF(A9="","",IF(MONTH(A9)<=3,"Q1",IF(MONTH(A9)<=6,"Q2",IF(MONTH(A9)<=9,"Q3","Q4"))))
G10: =IF(A10="","",IF(MONTH(A10)<=3,"Q1",IF(MONTH(A10)<=6,"Q2",IF(MONTH(A10)<=9,"Q3","Q4"))))
G11: =IF(A11="","",IF(MONTH(A11)<=3,"Q1",IF(MONTH(A11)<=6,"Q2",IF(MONTH(A11)<=9,"Q3","Q4"))))
G12: =IF(A12="","",IF(MONTH(A12)<=3,"Q1",IF(MONTH(A12)<=6,"Q2",IF(MONTH(A12)<=9,"Q3","Q4"))))
G13: =IF(A13="","",IF(MONTH(A13)<=3,"Q1",IF(MONTH(A13)<=6,"Q2",IF(MONTH(A13)<=9,"Q3","Q4"))))
G14: =IF(A14="","",IF(MONTH(A14)<=3,"Q1",IF(MONTH(A14)<=6,"Q2",IF(MONTH(A14)<=9,"Q3","Q4"))))
G15: =IF(A15="","",IF(MONTH(A15)<=3,"Q1",IF(MONTH(A15)<=6,"Q2",IF(MONTH(A15)<=9,"Q3","Q4"))))
G16: =IF(A16="","",IF(MONTH(A16)<=3,"Q1",IF(MONTH(A16)<=6,"Q2",IF(MONTH(A16)<=9,"Q3","Q4"))))
... G64: =IF(A64="","",IF(MONTH(A64)<=3,"Q1",IF(MONTH(A64)<=6,"Q2",IF(MONTH(A64)<=9,"Q3","Q4"))))
A65: TOTALS | E65: =SUM(E5:E64) | F65: =SUM(F5:F64) | G65: Net Profit: | H65: =E65-F65
A67: QUARTERLY SUMMARY
A68: Quarter | B68: Income | C68: Expenses | D68: Net Profit | E68: 20% IRPF Due
A69: Q1 | B69: =SUMPRODUCT((G5:G64="Q1")*(E5:E64)) | C69: =SUMPRODUCT((G5:G64="Q1")*(F5:F64)) | D69: =B69-C69 | E69: =MAX(D69*0.2,0)
A70: Q2 | B70: =SUMPRODUCT((G5:G64="Q2")*(E5:E64)) | C70: =SUMPRODUCT((G5:G64="Q2")*(F5:F64)) | D70: =B70-C70 | E70: =MAX(D70*0.2,0)
A71: Q3 | B71: =SUMPRODUCT((G5:G64="Q3")*(E5:E64)) | C71: =SUMPRODUCT((G5:G64="Q3")*(F5:F64)) | D71: =B71-C71 | E71: =MAX(D71*0.2,0)
A72: Q4 | B72: =SUMPRODUCT((G5:G64="Q4")*(E5:E64)) | C72: =SUMPRODUCT((G5:G64="Q4")*(F5:F64)) | D72: =B72-C72 | E72: =MAX(D72*0.2,0)
A74: KEY REMINDERS
A75: • Issue a numbered invoice (factura) for EVERY service — even to private individuals.
A76: • Keep ALL receipts. Expenses must be invoiced to your name (Andrew Griffiths, NIE Z1985059A).
A77: • Quarterly deadlines: Q1→1-20 Apr | Q2→1-20 Jul | Q3→1-20 Oct | Q4→1-20 Jan. File Modelo 130.
A78: • IVA (Modelo 303): Confirm with gestor if CNAE 8551 is IVA-exempt. May not need to charge 21%.
A79: • Tarifa plana: ~€80/month for first 12 months. After that, based on declared income.

Sheet 🧾 Invoices
A1: MR MALLORCA GOLF — INVOICE LOG 2026
A2: Issue a factura for every service. Numbering: MMG-2026-001, MMG-2026-002 ...
A4: Invoice # | B4: Date Issued | C4: Client Name | D4: Service Description | E4: Amount (€) | F4: IVA % | G4: IVA Amount | H4: Total (€) | I4: Paid? | J4: Payment Method
G5: =IF(E5="","",E5*F5) | H5: =IF(E5="","",E5+G5)
G6: =IF(E6="","",E6*F6) | H6: =IF(E6="","",E6+G6)
G7: =IF(E7="","",E7*F7) | H7: =IF(E7="","",E7+G7)
G8: =IF(E8="","",E8*F8) | H8: =IF(E8="","",E8+G8)
G9: =IF(E9="","",E9*F9) | H9: =IF(E9="","",E9+G9)
G10: =IF(E10="","",E10*F10) | H10: =IF(E10="","",E10+G10)
G11: =IF(E11="","",E11*F11) | H11: =IF(E11="","",E11+G11)
G12: =IF(E12="","",E12*F12) | H12: =IF(E12="","",E12+G12)
G13: =IF(E13="","",E13*F13) | H13: =IF(E13="","",E13+G13)
G14: =IF(E14="","",E14*F14) | H14: =IF(E14="","",E14+G14)
G15: =IF(E15="","",E15*F15) | H15: =IF(E15="","",E15+G15)
G16: =IF(E16="","",E16*F16) | H16: =IF(E16="","",E16+G16)
... G54: =IF(E54="","",E54*F54) | H54: =IF(E54="","",E54+G54)
A55: TOTALS | E55: =SUM(E5:E54) | G55: =SUM(G5:G54) | H55: =SUM(H5:H54)

Sheet 📊 Tax Calculator
A1: QUARTERLY TAX CALCULATOR — MODELO 130 (IRPF)
A2: Andy Griffiths · Baleares · Start date 26/05/2026 · IRPF rate 20% on net profit
A4: Item | B4: Q1 (Jan-Mar) | C4: Q2 (Apr-Jun) | D4: Q3 (Jul-Sep) | E4: Q4 (Oct-Dec)
A5: Total Income (from Ledger) | B5: =SUMPRODUCT(('📒 Ledger'!G5:G64="Q1")*('📒 Ledger'!E5:E64)) | C5: =SUMPRODUCT(('📒 Ledger'!G5:G64="Q2")*('📒 Ledger'!E5:E64)) | D5: =SUMPRODUCT(('📒 Ledger'!G5:G64="Q3")*('📒 Ledger'!E5:E64)) | E5: =SUMPRODUCT(('📒 Ledger'!G5:G64="Q4")*('📒 Ledger'!E5:E64))
A6: Total Expenses (from Ledger) | B6: =SUMPRODUCT(('📒 Ledger'!G5:G64="Q1")*('📒 Ledger'!F5:F64)) | C6: =SUMPRODUCT(('📒 Ledger'!G5:G64="Q2")*('📒 Ledger'!F5:F64)) | D6: =SUMPRODUCT(('📒 Ledger'!G5:G64="Q3")*('📒 Ledger'!F5:F64)) | E6: =SUMPRODUCT(('📒 Ledger'!G5:G64="Q4")*('📒 Ledger'!F5:F64))
A7: Net Profit | B7: =B5-B6 | C7: =C5-C6 | D7: =D5-D6 | E7: =E5-E6
A8: Cumulative Net Profit YTD | B8: =B7 | C8: =B8+C7 | D8: =C8+D7 | E8: =D8+E7
A9: 20% IRPF on Profit (gross) | B9: =MAX(B7*0.2,0) | C9: =MAX(C7*0.2,0) | D9: =MAX(D7*0.2,0) | E9: =MAX(E7*0.2,0)
A10: Previous Quarters Paid | B10: =0 | C10: =B9 | D10: =B9+C9 | E10: =B9+C9+D9
A11: Modelo 130 Payment Due | B11: =MAX(B9-B10,0) | C11: =MAX(C9-C10,0) | D11: =MAX(D9-D10,0) | E11: =MAX(E9-E10,0)
A13: SOCIAL SECURITY (RETA) — MONTHLY CUOTA
A14: Monthly Cuota (tarifa plana year 1) | B14: 80 | C14: Blue = enter actual amount from bank
A15: Months Active This Quarter | B15: 3 | C15: Adjust for partial quarters
A16: Total RETA Paid This Quarter | B16: =B14*B15
A17: Annual RETA Estimate | B17: =B14*12
A20: FILING DEADLINES
A21: Quarter | B21: Deadline | D21: Forms
A22: Q1 (Jan–Mar) | B22: 1–20 April | D22: Modelo 130 + 303 (if applicable)
A23: Q2 (Apr–Jun) | B23: 1–20 July | D23: Modelo 130 + 303 (if applicable)
A24: Q3 (Jul–Sep) | B24: 1–20 October | D24: Modelo 130 + 303 (if applicable)
A25: Q4 (Oct–Dec) | B25: 1–20 January | D25: Modelo 130 + 303 (if applicable)
A26: Annual Renta | B26: April–June 2027 | D26: Modelo 100 — reconciles all quarterly payments
A27: Modelo 720 | B27: Jan–April 2027 | D27: Foreign assets >€50k (if applicable)

Sheet 📐 Tax Brackets
A1: SPAIN INCOME TAX BRACKETS — BALEARES 2026
A2: Total tax = State rate + Baleares regional rate applied to same taxable base
A4: STATE TAX
A5: From (€) | B5: Up to (€) | C5: Cumulative Tax (€) | D5: Marginal Rate
A6: 0 | B6: 12450 | C6: 1182.75 | D6: 0.095
A7: 12450 | B7: 20200 | C7: 2112.75 | D7: 0.12
A8: 20200 | B8: 35200 | C8: 4362.75 | D8: 0.15
A9: 35200 | B9: 60000 | C9: 8950.75 | D9: 0.185
A10: 60000 | B10: 300000 | C10: 62950.75 | D10: 0.225
A11: 300000 | B11: onwards | C11: — | D11: 0.245
A13: BALEARES REGIONAL TAX
A14: From (€) | B14: Up to (€) | C14: Cumulative Tax (€) | D14: Marginal Rate
A15: 0 | B15: 10000 | C15: 900 | D15: 0.09
A16: 10000 | B16: 18000 | C16: 1800 | D16: 0.1125
A17: 18000 | B17: 30000 | C17: 3510 | D17: 0.1425
A18: 30000 | B18: 48000 | C18: 6660 | D18: 0.175
A19: 48000 | B19: 70000 | C19: 10840 | D19: 0.19
A20: 70000 | B20: 90000 | C20: 15190 | D20: 0.2175
A21: 90000 | B21: 120000 | C21: 22015 | D21: 0.2275
A22: 120000 | B22: 175000 | C22: 35077.5 | D22: 0.2375
A23: 175000 | B23: onwards | C23: — | D23: 0.2475
A24: EXAMPLE: €76,000 TAXABLE INCOME (Income €100k - Expenses €24k)
A25: State tax (up to €60k) | B25: 8950.75
A26: State tax on remaining €16k @ 22.5% | B26: =16000*0.225
A27: Total state tax | B27: =B25+B26
A28: Baleares tax (up to €70k) | B28: 15190
A29: Baleares tax on remaining €6k @ 21.75% | B29: =6000*0.2175
A30: Total Baleares tax | B30: =B28+B29
A31: TOTAL TAX OWED | B31: =B27+B30
A32: Effective rate on €76k | B32: =B31/76000

Sheet ❓ Gestor Questions
A1: QUESTIONS FOR GESTOR MEETING
A2: Print this sheet and take it to the meeting. Fill in 'Answer / Notes' column.
A4: # | B4: Question | C4: Answer / Notes | D4: Done?
B5: IVA / VAT
A6: 1 | B6: Is CNAE 8551 / IAE 826 exempt from IVA under Art.20 Ley del IVA? Under what conditions?
A7: 2 | B7: If IVA-exempt, do I still need to file Modelo 303? Or any IVA model?
A8: 3 | B8: If a golf club pays me (empresa), do I charge IVA differently than for a private client?
B9: IRPF / QUARTERLY TAX
A10: 5 | B10: Do I apply retención on my invoices? Which clients require it (only empresas)?
A11: 6 | B11: What retención % applies to my activity code?
A12: 7 | B12: Walk me through Modelo 130: do I file it myself on Sede Electrónica with Cl@ve?
A13: 8 | B13: Are there any deductions on Modelo 130 beyond just income minus expenses?
B14: EXPENSES — CONFIRM DEDUCTIBILITY
A15: 10 | B15: Golf balls, tees, training aids used for coaching — fully deductible?
A16: 11 | B16: Transport to courses where I coach (fuel / public transport) — what evidence needed?
A17: 12 | B17: Mobile phone and internet — what % can I deduct? Do I need a separate work contract?
A18: 13 | B18: Website hosting, domain (mrmallorcagolf.com) — fully deductible?
A19: 14 | B19: Professional liability insurance — fully deductible?
A20: 15 | B20: Home office — can I deduct a % of rent/utilities? How complex is this?
A21: 16 | B21: Launch monitor / video analysis equipment — one-off deduction or amortised?
B22: RECORD-KEEPING
A23: 18 | B23: What must my libro de ingresos y gastos contain? Is a spreadsheet acceptable?
A24: 19 | B24: How long must I keep receipts and invoices?
A25: 20 | B25: Receipts from private individuals — do I need their full address on invoices?
B26: INVOICING
A27: 22 | B27: For private clients with no NIF — what minimum info is required on the factura?
A28: 23 | B28: Is a numbered PDF template acceptable, or must I use official software?
A29: 24 | B29: Cobros via Bizum or cash — any special rules or limits for autónomos?
B30: SOCIAL SECURITY / CUOTA
A31: 26 | B31: My tarifa plana started 26/05/2026 — exactly when does it end and what happens next?
A32: 27 | B32: I declared €670/month. What triggers a change to my cotización base?
A33: 28 | B33: Cuota Cero Baleares — I applied before 10 June. How does it interact with tarifa plana?
B34: ANNUAL RENTA (MODELO 100)
A35: 30 | B35: For annual renta April-June 2027: do my quarterly Modelo 130 payments offset it fully?
A36: 31 | B36: Any Baleares-specific deductions I should know about for 2026?
A37: 32 | B37: Do I need Modelo 720 (foreign assets)? What threshold triggers it?
B38: PRACTICALITIES
A39: 34 | B39: If I manage my own invoicing and bring you a clean quarterly spreadsheet — what's your fee for filing only?
A40: 35 | B40: Which platform do you recommend for DIY invoicing (free/cheap)?
A41: 36 | B41: Any other obligations I've missed for my specific situation?
